{
    "items": [
        {
            "link": "https://spb.hh.ru/vacancy/80580029?from=vacancy_search_list&query=python+flask+django",
            "salary": "140 000 – 250 000 руб.",
            "company": "AERODISK",
            "city": "Москва, Калужская"
        },
        {
            "link": "https://spb.hh.ru/vacancy/80400921?from=vacancy_search_list&query=python+flask+django",
            "salary": "70 000 – 100 000 руб.",
            "company": "РусЭкспресс",
            "city": "Москва"
        },
        {
            "link": "https://spb.hh.ru/vacancy/80050718?from=vacancy_search_list&query=python+flask+django",
            "salary": "60 000 – 140 000 руб.",
            "company": "ООО РА Дельта",
            "city": "Москва"
        },
        {
            "link": "https://spb.hh.ru/vacancy/79895487?from=vacancy_search_list&query=python+flask+django",
            "salary": "190 000 – 220 000 руб.",
            "company": "ЧУ ДО Московская школа программистов",
            "city": "Москва, Ботанический сад и еще 1 "
        },
        {
            "link": "https://spb.hh.ru/vacancy/80821125?from=vacancy_search_list&query=python+flask+django",
            "salary": "Не указано",
            "company": "SayHire.agency",
            "city": "Москва"
        },
        {
            "link": "https://spb.hh.ru/vacancy/79817887?from=vacancy_search_list&query=python+flask+django",
            "salary": "Не указано",
            "company": "WelbeX",
            "city": "Москва"
        },
        {
            "link": "https://spb.hh.ru/vacancy/80024403?from=vacancy_search_list&query=python+flask+django",
            "salary": "200 000 – 350 000 руб.",
            "company": "Carbon Soft",
            "city": "Москва, Проспект Вернадского"
        },
        {
            "link": "https://spb.hh.ru/vacancy/77601657?from=vacancy_search_list&query=python+flask+django",
            "salary": "Не указано",
            "company": "Максмарт",
            "city": "Москва"
        },
        {
            "link": "https://spb.hh.ru/vacancy/80672896?from=vacancy_search_list&query=python+flask+django",
            "salary": "до 320 000 руб.",
            "company": "Точка",
            "city": "Москва"
        },
        {
            "link": "https://spb.hh.ru/vacancy/80672968?from=vacancy_search_list&query=python+flask+django",
            "salary": "от 60 000 руб.",
            "company": "ООО Виста",
            "city": "Санкт-Петербург"
        },
        {
            "link": "https://spb.hh.ru/vacancy/80679805?from=vacancy_search_list&query=python+flask+django",
            "salary": "Не указано",
            "company": "Oil and Gas Production Tools",
            "city": "Санкт-Петербург"
        },
        {
            "link": "https://spb.hh.ru/vacancy/80867007?from=vacancy_search_list&query=python+flask+django",
            "salary": "Не указано",
            "company": "Beorg",
            "city": "Москва, Технопарк"
        },
        {
            "link": "https://spb.hh.ru/vacancy/80582319?from=vacancy_search_list&query=python+flask+django",
            "salary": "Не указано",
            "company": "АО Лотереи Москвы",
            "city": "Москва"
        },
        {
            "link": "https://spb.hh.ru/vacancy/80053266?from=vacancy_search_list&query=python+flask+django",
            "salary": "Не указано",
            "company": "Lesta Games",
            "city": "Москва, Савёловская и еще 2 "
        },
        {
            "link": "https://spb.hh.ru/vacancy/70052938?from=vacancy_search_list&query=python+flask+django",
            "salary": "Не указано",
            "company": "Группа компаний Астра",
            "city": "Москва, Верхние Котлы и еще 1 "
        },
        {
            "link": "https://spb.hh.ru/vacancy/79219903?from=vacancy_search_list&query=python+flask+django",
            "salary": "до 350 000 руб.",
            "company": "Фаворит, Международный кадровый центр",
            "city": "Москва"
        },
        {
            "link": "https://spb.hh.ru/vacancy/80578992?from=vacancy_search_list&query=python+flask+django",
            "salary": "Не указано",
            "company": "ООО Napoleon IT",
            "city": "Санкт-Петербург"
        },
        {
            "link": "https://spb.hh.ru/vacancy/80506144?from=vacancy_search_list&query=python+flask+django",
            "salary": "от 200 000 руб.",
            "company": "ООО ВижнЛабс (VisionLabs)",
            "city": "Москва"
        },
        {
            "link": "https://spb.hh.ru/vacancy/80870187?from=vacancy_search_list&query=python+flask+django",
            "salary": "Не указано",
            "company": "ООО WaveAccess",
            "city": "Санкт-Петербург"
        },
        {
            "link": "https://spb.hh.ru/vacancy/80648193?from=vacancy_search_list&query=python+flask+django",
            "salary": "200 000 – 350 000 руб.",
            "company": "ООО Кадровый центр Президент",
            "city": "Москва, Бауманская"
        },
        {
            "link": "https://spb.hh.ru/vacancy/80517879?from=vacancy_search_list&query=python+flask+django",
            "salary": "Не указано",
            "company": "Positive Technologies",
            "city": "Санкт-Петербург"
        },
        {
            "link": "https://spb.hh.ru/vacancy/75697177?from=vacancy_search_list&query=python+flask+django",
            "salary": "Не указано",
            "company": "АО АСТ",
            "city": "Москва, Волгоградский проспект"
        },
        {
            "link": "https://spb.hh.ru/vacancy/80316527?from=vacancy_search_list&query=python+flask+django",
            "salary": "Не указано",
            "company": "Deventica",
            "city": "Санкт-Петербург"
        },
        {
            "link": "https://spb.hh.ru/vacancy/80198541?from=vacancy_search_list&query=python+flask+django",
            "salary": "Не указано",
            "company": "ИП Серяков Виктор Юрьевич",
            "city": "Москва"
        },
        {
            "link": "https://spb.hh.ru/vacancy/80729828?from=vacancy_search_list&query=python+flask+django",
            "salary": "Не указано",
            "company": "HEADS and HANDS",
            "city": "Санкт-Петербург"
        },
        {
            "link": "https://spb.hh.ru/vacancy/80604425?from=vacancy_search_list&query=python+flask+django",
            "salary": "Не указано",
            "company": "ООО Цифровые Сервисы",
            "city": "Москва"
        },
        {
            "link": "https://spb.hh.ru/vacancy/77958176?from=vacancy_search_list&query=python+flask+django",
            "salary": "Не указано",
            "company": "INSITECH Development",
            "city": "Москва, Савёловская"
        },
        {
            "link": "https://spb.hh.ru/vacancy/79210452?from=vacancy_search_list&query=python+flask+django",
            "salary": "Не указано",
            "company": "Центр Методического Обеспечения Оптимизации Процессов Государственного Управления в Московской области",
            "city": "Москва"
        },
        {
            "link": "https://spb.hh.ru/vacancy/77296899?from=vacancy_search_list&query=python+flask+django",
            "salary": "до 300 000 руб.",
            "company": "SberTech",
            "city": "Москва, Кожуховская"
        },
        {
            "link": "https://spb.hh.ru/vacancy/79165199?from=vacancy_search_list&query=python+flask+django",
            "salary": "Не указано",
            "company": "INSITECH Development",
            "city": "Санкт-Петербург"
        },
        {
            "link": "https://spb.hh.ru/vacancy/80122527?from=vacancy_search_list&query=python+flask+django",
            "salary": "Не указано",
            "company": "Сбер. IT",
            "city": "Москва"
        },
        {
            "link": "https://spb.hh.ru/vacancy/79848315?from=vacancy_search_list&query=python+flask+django",
            "salary": "от 400 000 руб.",
            "company": "АО Международный аэропорт Шереметьево",
            "city": "Москва, Красные ворота"
        },
        {
            "link": "https://spb.hh.ru/vacancy/79314802?from=vacancy_search_list&query=python+flask+django",
            "salary": "Не указано",
            "company": "Интерфакс",
            "city": "Москва"
        },
        {
            "link": "https://spb.hh.ru/vacancy/80714456?from=vacancy_search_list&query=python+flask+django",
            "salary": "от 90 000 руб.",
            "company": "ООО НПК РВТС",
            "city": "Москва"
        },
        {
            "link": "https://spb.hh.ru/vacancy/79917370?from=vacancy_search_list&query=python+flask+django",
            "salary": "200 000 – 350 000 руб.",
            "company": "ООО Кадровый центр Президент",
            "city": "Москва"
        },
        {
            "link": "https://spb.hh.ru/vacancy/79732131?from=vacancy_search_list&query=python+flask+django",
            "salary": "Не указано",
            "company": "ООО БИЗНЕС КОННЕКТ",
            "city": "Москва"
        },
        {
            "link": "https://spb.hh.ru/vacancy/79584451?from=vacancy_search_list&query=python+flask+django",
            "salary": "Не указано",
            "company": "Центр Методического Обеспечения Оптимизации Процессов Государственного Управления в Московской области",
            "city": "Москва"
        },
        {
            "link": "https://spb.hh.ru/vacancy/78374313?from=vacancy_search_list&query=python+flask+django",
            "salary": "Не указано",
            "company": "Сбер. IT",
            "city": "Москва"
        },
        {
            "link": "https://spb.hh.ru/vacancy/78743031?from=vacancy_search_list&query=python+flask+django",
            "salary": "до 180 000 руб.",
            "company": "АО НИИ МАСШТАБ",
            "city": "Санкт-Петербург"
        },
        {
            "link": "https://spb.hh.ru/vacancy/80168664?from=vacancy_search_list&query=python+flask+django",
            "salary": "от 150 000 руб.",
            "company": "ООО Lerteco",
            "city": "Санкт-Петербург"
        },
        {
            "link": "https://spb.hh.ru/vacancy/76849150?from=vacancy_search_list&query=python+flask+django",
            "salary": "Не указано",
            "company": "ООО Бристоль, сеть магазинов",
            "city": "Москва"
        },
        {
            "link": "https://spb.hh.ru/vacancy/79730278?from=vacancy_search_list&query=python+flask+django",
            "salary": "140 000 – 210 000 руб.",
            "company": "Surf IT",
            "city": "Санкт-Петербург"
        },
        {
            "link": "https://spb.hh.ru/vacancy/78910554?from=vacancy_search_list&query=python+flask+django",
            "salary": "Не указано",
            "company": "YADRO",
            "city": "Санкт-Петербург"
        },
        {
            "link": "https://spb.hh.ru/vacancy/79739335?from=vacancy_search_list&query=python+flask+django",
            "salary": "Не указано",
            "company": "ООО «РУСАГРО», Группа компаний",
            "city": "Москва"
        },
        {
            "link": "https://spb.hh.ru/vacancy/79807693?from=vacancy_search_list&query=python+flask+django",
            "salary": "Не указано",
            "company": " Schlumberger. АО ИКФ-Сервис. Офис",
            "city": "Москва"
        },
        {
            "link": "https://spb.hh.ru/vacancy/80049283?from=vacancy_search_list&query=python+flask+django",
            "salary": "от 45 000 руб.",
            "company": "ООО Траектория",
            "city": "Санкт-Петербург, Лесная и еще 3 "
        },
        {
            "link": "https://spb.hh.ru/vacancy/80780414?from=vacancy_search_list&query=python+flask+django",
            "salary": "80 000 – 200 000 руб.",
            "company": "ИП Гусев Святослав Олегович",
            "city": "Москва"
        },
        {
            "link": "https://spb.hh.ru/vacancy/80780415?from=vacancy_search_list&query=python+flask+django",
            "salary": "80 000 – 200 000 руб.",
            "company": "ИП Гусев Святослав Олегович",
            "city": "Санкт-Петербург"
        },
        {
            "link": "https://spb.hh.ru/vacancy/80610805?from=vacancy_search_list&query=python+flask+django",
            "salary": "Не указано",
            "company": "ООО Систем Дизайн Индастрис",
            "city": "Санкт-Петербург"
        },
        {
            "link": "https://spb.hh.ru/vacancy/67864415?from=vacancy_search_list&query=python+flask+django",
            "salary": "до 80 000 руб.",
            "company": "Hexlet",
            "city": "Москва"
        },
        {
            "link": "https://spb.hh.ru/vacancy/77302829?from=vacancy_search_list&query=python+flask+django",
            "salary": "Не указано",
            "company": "ООО АйТи Интеллект",
            "city": "Москва"
        },
        {
            "link": "https://spb.hh.ru/vacancy/79871781?from=vacancy_search_list&query=python+flask+django",
            "salary": "от 140 000 руб.",
            "company": "АО Гринатом",
            "city": "Москва"
        },
        {
            "link": "https://spb.hh.ru/vacancy/80790789?from=vacancy_search_list&query=python+flask+django",
            "salary": "Не указано",
            "company": "Sape",
            "city": "Москва"
        },
        {
            "link": "https://spb.hh.ru/vacancy/79999266?from=vacancy_search_list&query=python+flask+django",
            "salary": "180 000 – 250 000 руб.",
            "company": "ООО РА Дельта",
            "city": "Москва"
        },
        {
            "link": "https://spb.hh.ru/vacancy/80232704?from=vacancy_search_list&query=python+flask+django",
            "salary": "Не указано",
            "company": "Группа Самолет",
            "city": "Москва"
        },
        {
            "link": "https://spb.hh.ru/vacancy/80649106?from=vacancy_search_list&query=python+flask+django",
            "salary": "Не указано",
            "company": "VK, ВКонтакте",
            "city": "Москва"
        },
        {
            "link": "https://spb.hh.ru/vacancy/80649107?from=vacancy_search_list&query=python+flask+django",
            "salary": "Не указано",
            "company": "VK, ВКонтакте",
            "city": "Санкт-Петербург"
        },
        {
            "link": "https://spb.hh.ru/vacancy/80301039?from=vacancy_search_list&query=python+flask+django",
            "salary": "Не указано",
            "company": "ИВ РОШЕ",
            "city": "Москва, Белорусская"
        },
        {
            "link": "https://spb.hh.ru/vacancy/79582840?from=vacancy_search_list&query=python+flask+django",
            "salary": "Не указано",
            "company": "Сбер. IT",
            "city": "Москва, Кутузовская и еще 1 "
        },
        {
            "link": "https://spb.hh.ru/vacancy/72312345?from=vacancy_search_list&query=python+flask+django",
            "salary": "до 400 000 руб.",
            "company": "Rubbles",
            "city": "Москва"
        }
    ]
}